[
  {
    "FOOD": "0.000034000000",
    "GOLD": "0.000035500000",
    "WOOD": "0.000027665000",
    "date_update": 1721264833,
    "is_cash": true
  },
  {
    "FOOD": "0.000033945946",
    "GOLD": "0.000035400000",
    "WOOD": "0.000027600000",
    "date_update": 1721268566,
    "is_cash": true
  },
  {
    "FOOD": "0.000033945946",
    "GOLD": "0.000035400000",
    "WOOD": "0.000027600000",
    "date_update": 1721270495,
    "is_cash": true
  },
  {
    "FOOD": "0.000033945946",
    "GOLD": "0.000035400000",
    "WOOD": "0.000027666667",
    "date_update": 1721271120,
    "is_cash": true
  },
  {
    "date_update": 1721272203,
    "FOOD": "0.000034000000",
    "GOLD": "0.000035400000",
    "WOOD": "0.000027666667",
    "STONE": "0.000029666667",
    "PLANKS": "0.014500000000",
    "SOUP": "0.030000000000",
    "INGOT": "0.017500000000",
    "is_cash": false
  },
  {
    "FOOD": "0.000035000000",
    "GOLD": "0.000035400000",
    "WOOD": "0.000027666667",
    "date_update": 1721273479,
    "is_cash": true
  },
  {
    "FOOD": "0.000035000000",
    "GOLD": "0.000035400000",
    "WOOD": "0.000027666667",
    "date_update": 1721274127,
    "is_cash": true
  },
  {
    "date_update": 1721274700,
    "FOOD": "0.000035000000",
    "GOLD": "0.000035400000",
    "WOOD": "0.000027666667",
    "STONE": "0.000029666667",
    "PLANKS": "0.014500000000",
    "SOUP": "0.030000000000",
    "INGOT": "0.017500000000",
    "is_cash": true
  },
  {
    "date_update": 1721275766,
    "FOOD": "0.000035000000",
    "GOLD": "0.000035400000",
    "WOOD": "0.000027666667",
    "STONE": "0.000029666667",
    "PLANKS": "0.014500000000",
    "SOUP": "0.030000000000",
    "INGOT": "0.017500000000",
    "is_cash": true
  },
  {
    "FOOD": "0.000035000000",
    "GOLD": "0.000035500000",
    "WOOD": "0.000027000000",
    "date_update": 1721276976,
    "is_cash": true
  },
  {
    "date_update": 1721277699,
    "FOOD": "0.000035000000",
    "GOLD": "0.000035500000",
    "WOOD": "0.000027666667",
    "STONE": "0.000029666667",
    "PLANKS": "0.014500000000",
    "SOUP": "0.030000000000",
    "INGOT": "0.017500000000",
    "is_cash": false
  },
  {
    "FOOD": "0.000035000000",
    "GOLD": "0.000035500000",
    "WOOD": "0.000027666667",
    "date_update": 1721278275,
    "is_cash": true
  },
  {
    "FOOD": "0.000035000000",
    "GOLD": "0.000035500000",
    "WOOD": "0.000027666667",
    "date_update": 1721279248,
    "is_cash": true
  },
  {
    "FOOD": "0.000034933333",
    "GOLD": "0.000035333333",
    "WOOD": "0.000027663333",
    "date_update": 1721280434,
    "is_cash": true
  },
  {
    "FOOD": "0.000034933333",
    "GOLD": "0.000035333333",
    "WOOD": "0.000027663333",
    "date_update": 1721281050,
    "is_cash": true
  },
  {
    "FOOD": "0.000034920000",
    "GOLD": "0.000035333333",
    "WOOD": "0.000027666667",
    "date_update": 1721281644,
    "is_cash": true
  },
  {
    "FOOD": "0.000034000000",
    "GOLD": "0.000035333333",
    "WOOD": "0.000027666667",
    "date_update": 1721282231,
    "is_cash": true
  },
  {
    "date_update": 1721283912,
    "FOOD": "0.000034888889",
    "GOLD": "0.000034999627",
    "WOOD": "0.000027666667",
    "STONE": "0.000029666667",
    "PLANKS": "0.014000000000",
    "SOUP": "0.030000000000",
    "INGOT": "0.017500000000",
    "is_cash": true
  },
  {
    "FOOD": "0.000034888889",
    "GOLD": "0.000034999627",
    "WOOD": "0.000027666667",
    "date_update": 1721284809,
    "is_cash": true
  },
  {
    "FOOD": "0.000034888889",
    "GOLD": "0.000034999627",
    "WOOD": "0.000027666667",
    "date_update": 1721285387,
    "is_cash": true
  },
  {
    "date_update": 1721285962,
    "FOOD": "0.000034888889",
    "GOLD": "0.000034999627",
    "WOOD": "0.000027666667",
    "STONE": "0.000029666667",
    "PLANKS": "0.014000000000",
    "SOUP": "0.030000000000",
    "INGOT": "0.017500000000",
    "is_cash": true
  },
  {
    "FOOD": "0.000034888889",
    "GOLD": "0.000033333333",
    "WOOD": "0.000027650000",
    "date_update": 1721287193,
    "is_cash": true
  }
]
