[
  {
    "date_update": 1731977944,
    "FOOD": 6.8e-05,
    "GOLD": 5.455e-05,
    "WOOD": 6.435e-05,
    "STONE": 8.333e-05,
    "PLANKS": 0.08489,
    "SOUP": 0.0499,
    "INGOT": 0.0598,
    "is_cash": true
  },
  {
    "date_update": 1731983618,
    "FOOD": 6.8e-05,
    "GOLD": 5.455e-05,
    "WOOD": 6.4e-05,
    "STONE": 8.333e-05,
    "PLANKS": 0.08489,
    "SOUP": 0.0499,
    "INGOT": 0.0598,
    "is_cash": true
  },
  {
    "date_update": 1731986244,
    "FOOD": 6.8e-05,
    "GOLD": 5.455e-05,
    "WOOD": 6.395e-05,
    "STONE": 8.333e-05,
    "PLANKS": 0.08489,
    "SOUP": 0.0499,
    "INGOT": 0.0598,
    "is_cash": false
  },
  {
    "FOOD": "0.000068000000",
    "GOLD": "0.000054550000",
    "WOOD": "0.000063947368",
    "date_update": 1731988014,
    "is_cash": true
  },
  {
    "date_update": 1731988764,
    "FOOD": 6.8e-05,
    "GOLD": 5.455e-05,
    "WOOD": 6.395e-05,
    "STONE": 8.333e-05,
    "PLANKS": 0.08489,
    "SOUP": 0.0499,
    "INGOT": 0.0598,
    "is_cash": false
  },
  {
    "date_update": 1731990607,
    "FOOD": 6.8e-05,
    "GOLD": 5.455e-05,
    "WOOD": 5.5e-05,
    "STONE": 8.333e-05,
    "PLANKS": 0.08489,
    "SOUP": 0.0499,
    "INGOT": 0.0598,
    "is_cash": true
  },
  {
    "date_update": 1731991586,
    "FOOD": 6.8e-05,
    "GOLD": 5.455e-05,
    "WOOD": 5.5e-05,
    "STONE": 8.333e-05,
    "PLANKS": 0.08489,
    "SOUP": 0.0499,
    "INGOT": 0.0598,
    "is_cash": false
  },
  {
    "date_update": 1731992339,
    "FOOD": 6.8e-05,
    "GOLD": 5.455e-05,
    "WOOD": 5.5e-05,
    "STONE": 8.333e-05,
    "PLANKS": 0.08489,
    "SOUP": 0.0499,
    "INGOT": 0.0598,
    "is_cash": false
  },
  {
    "date_update": 1731993975,
    "FOOD": 6.8e-05,
    "GOLD": 5.455e-05,
    "WOOD": 5.493e-05,
    "STONE": 8.333e-05,
    "PLANKS": 0.08489,
    "SOUP": 0.0499,
    "INGOT": 0.0598,
    "is_cash": false
  },
  {
    "date_update": 1731994934,
    "FOOD": 6.8e-05,
    "GOLD": 5.455e-05,
    "WOOD": 5.493e-05,
    "STONE": 8.333e-05,
    "PLANKS": 0.08489,
    "SOUP": 0.0499,
    "INGOT": 0.0598,
    "is_cash": false
  },
  {
    "FOOD": "0.000068000000",
    "GOLD": "0.000054550000",
    "WOOD": "0.000054054054",
    "date_update": 1731995677,
    "is_cash": true
  },
  {
    "date_update": 1731997800,
    "FOOD": 6.8e-05,
    "GOLD": 5.455e-05,
    "WOOD": 5.405e-05,
    "STONE": 8.333e-05,
    "PLANKS": 0.08489,
    "SOUP": 0.0499,
    "INGOT": 0.0598,
    "is_cash": true
  },
  {
    "date_update": 1731998951,
    "FOOD": 6.8e-05,
    "GOLD": 5.455e-05,
    "WOOD": 5.493e-05,
    "STONE": 8.333e-05,
    "PLANKS": 0.08489,
    "SOUP": 0.0499,
    "INGOT": 0.055,
    "is_cash": true
  },
  {
    "date_update": 1732000211,
    "FOOD": 6.8e-05,
    "GOLD": 5.455e-05,
    "WOOD": 5.446e-05,
    "STONE": 8.333e-05,
    "PLANKS": 0.08489,
    "SOUP": 0.0499,
    "INGOT": 0.055,
    "is_cash": false
  },
  {
    "date_update": 1732001409,
    "FOOD": 6.8e-05,
    "GOLD": 5.455e-05,
    "WOOD": 5.446e-05,
    "STONE": 8.333e-05,
    "PLANKS": 0.08489,
    "SOUP": 0.0499,
    "INGOT": 0.055,
    "is_cash": true
  },
  {
    "FOOD": "0.000067998134",
    "GOLD": "0.000054550000",
    "WOOD": "0.000054460000",
    "date_update": 1732002149,
    "is_cash": true
  },
  {
    "date_update": 1732002907,
    "FOOD": 6.8e-05,
    "GOLD": 5.455e-05,
    "WOOD": 5.446e-05,
    "STONE": 8.333e-05,
    "PLANKS": 0.08489,
    "SOUP": 0.0499,
    "INGOT": 0.0525,
    "is_cash": true
  },
  {
    "date_update": 1732004945,
    "FOOD": 6.8e-05,
    "GOLD": 5.455e-05,
    "WOOD": 5.446e-05,
    "STONE": 8.333e-05,
    "PLANKS": 0.08489,
    "SOUP": 0.0499,
    "INGOT": 0.0525,
    "is_cash": true
  },
  {
    "date_update": 1732006132,
    "FOOD": 6.8e-05,
    "GOLD": 5.455e-05,
    "WOOD": 5.445e-05,
    "STONE": 8.333e-05,
    "PLANKS": 0.08489,
    "SOUP": 0.0499,
    "INGOT": 0.0525,
    "is_cash": true
  },
  {
    "FOOD": "0.000068000000",
    "GOLD": "0.000054550000",
    "WOOD": "0.000054452632",
    "date_update": 1732007390,
    "is_cash": true
  },
  {
    "FOOD": "0.000068000000",
    "GOLD": "0.000054550000",
    "WOOD": "0.000054460000",
    "date_update": 1732008689,
    "is_cash": true
  },
  {
    "FOOD": "0.000067900000",
    "GOLD": "0.000054550000",
    "WOOD": "0.000054460000",
    "date_update": 1732009474,
    "is_cash": true
  },
  {
    "date_update": 1732010227,
    "FOOD": 6.79e-05,
    "GOLD": 5.455e-05,
    "WOOD": 5.5e-05,
    "STONE": 8.333e-05,
    "PLANKS": 0.08489,
    "SOUP": 0.0499,
    "INGOT": 0.05,
    "is_cash": false
  },
  {
    "date_update": 1732012110,
    "FOOD": 6.79e-05,
    "GOLD": 5.455e-05,
    "WOOD": 5.494e-05,
    "STONE": 8.333e-05,
    "PLANKS": 0.08489,
    "SOUP": 0.0499,
    "INGOT": 0.05,
    "is_cash": false
  },
  {
    "FOOD": "0.000067900000",
    "GOLD": "0.000054550000",
    "WOOD": "0.000055000000",
    "date_update": 1732013207,
    "is_cash": true
  },
  {
    "FOOD": "0.000067900000",
    "GOLD": "0.000054550000",
    "WOOD": "0.000055000000",
    "date_update": 1732013954,
    "is_cash": true
  },
  {
    "FOOD": "0.000067900000",
    "GOLD": "0.000054550000",
    "WOOD": "0.000055000000",
    "date_update": 1732015292,
    "is_cash": true
  },
  {
    "date_update": 1732016127,
    "FOOD": 6.79e-05,
    "GOLD": 5.455e-05,
    "WOOD": 5.5e-05,
    "STONE": 8.333e-05,
    "PLANKS": 0.08489,
    "SOUP": 0.0499,
    "INGOT": 0.05,
    "is_cash": false
  },
  {
    "date_update": 1732016881,
    "FOOD": 6.79e-05,
    "GOLD": 5.455e-05,
    "WOOD": 5.5e-05,
    "STONE": 8.333e-05,
    "PLANKS": 0.08489,
    "SOUP": 0.0499,
    "INGOT": 0.05,
    "is_cash": true
  },
  {
    "date_update": 1732018421,
    "FOOD": 6.5e-05,
    "GOLD": 5.455e-05,
    "WOOD": 5.5e-05,
    "STONE": 8.333e-05,
    "PLANKS": 0.08489,
    "SOUP": 0.0499,
    "INGOT": 0.05,
    "is_cash": true
  },
  {
    "date_update": 1732020987,
    "FOOD": 6.5e-05,
    "GOLD": 5.455e-05,
    "WOOD": 5.5e-05,
    "STONE": 8.333e-05,
    "PLANKS": 0.08489,
    "SOUP": 0.0499,
    "INGOT": 0.05,
    "is_cash": true
  },
  {
    "date_update": 1732023131,
    "FOOD": 6.5e-05,
    "GOLD": 5.455e-05,
    "WOOD": 5.5e-05,
    "STONE": 8.333e-05,
    "PLANKS": 0.08489,
    "SOUP": 0.0499,
    "INGOT": 0.05,
    "is_cash": true
  },
  {
    "date_update": 1732023998,
    "FOOD": 6.5e-05,
    "GOLD": 5.455e-05,
    "WOOD": 5.5e-05,
    "STONE": 8.333e-05,
    "PLANKS": 0.08489,
    "SOUP": 0.0499,
    "INGOT": 0.05,
    "is_cash": false
  },
  {
    "date_update": 1732024743,
    "FOOD": 6.5e-05,
    "GOLD": 5.455e-05,
    "WOOD": 5.5e-05,
    "STONE": 8.333e-05,
    "PLANKS": 0.08489,
    "SOUP": 0.0499,
    "INGOT": 0.05,
    "is_cash": false
  }
]
