[
  {
    "FOOD": "0.000063000000",
    "GOLD": "0.000054550000",
    "WOOD": "0.000051850000",
    "date_update": 1732065032,
    "is_cash": true
  },
  {
    "date_update": 1732070198,
    "FOOD": 6.3e-05,
    "GOLD": 5.455e-05,
    "WOOD": 5.185e-05,
    "STONE": 8.333e-05,
    "PLANKS": 0.08,
    "SOUP": 0.0499,
    "INGOT": 0.0375,
    "is_cash": true
  },
  {
    "date_update": 1732072666,
    "FOOD": 6.3e-05,
    "GOLD": 5.455e-05,
    "WOOD": 5.185e-05,
    "STONE": 8.333e-05,
    "PLANKS": 0.08,
    "SOUP": 0.0499,
    "INGOT": 0.0375,
    "is_cash": false
  },
  {
    "FOOD": "0.000063000000",
    "GOLD": "0.000054550000",
    "WOOD": "0.000048476454",
    "date_update": 1732074250,
    "is_cash": true
  },
  {
    "FOOD": "0.000063000000",
    "GOLD": "0.000050000000",
    "WOOD": "0.000048476454",
    "date_update": 1732075000,
    "is_cash": true
  },
  {
    "date_update": 1732076958,
    "FOOD": 6.3e-05,
    "GOLD": 5.455e-05,
    "WOOD": 4.848e-05,
    "STONE": 8.333e-05,
    "PLANKS": 0.08,
    "SOUP": 0.0499,
    "INGOT": 0.0375,
    "is_cash": false
  },
  {
    "date_update": 1732077984,
    "FOOD": 6.3e-05,
    "GOLD": 5.455e-05,
    "WOOD": 4.848e-05,
    "STONE": 8.333e-05,
    "PLANKS": 0.08,
    "SOUP": 0.0499,
    "INGOT": 0.0375,
    "is_cash": true
  },
  {
    "date_update": 1732078741,
    "FOOD": 6.3e-05,
    "GOLD": 5.455e-05,
    "WOOD": 4.848e-05,
    "STONE": 8.333e-05,
    "PLANKS": 0.08,
    "SOUP": 0.0499,
    "INGOT": 0.0375,
    "is_cash": false
  },
  {
    "date_update": 1732080380,
    "FOOD": 6.3e-05,
    "GOLD": 5.455e-05,
    "WOOD": 4.848e-05,
    "STONE": 8.333e-05,
    "PLANKS": 0.08,
    "SOUP": 0.0499,
    "INGOT": 0.0375,
    "is_cash": true
  },
  {
    "date_update": 1732081359,
    "FOOD": 6.3e-05,
    "GOLD": 5.455e-05,
    "WOOD": 4.848e-05,
    "STONE": 8.333e-05,
    "PLANKS": 0.08,
    "SOUP": 0.0499,
    "INGOT": 0.0375,
    "is_cash": true
  },
  {
    "FOOD": "0.000063000000",
    "GOLD": "0.000054550000",
    "WOOD": "0.000048480000",
    "date_update": 1732082108,
    "is_cash": true
  },
  {
    "FOOD": "0.000063000000",
    "GOLD": "0.000054550000",
    "WOOD": "0.000048480000",
    "date_update": 1732084301,
    "is_cash": true
  },
  {
    "date_update": 1732085398,
    "FOOD": 6.3e-05,
    "GOLD": 5.455e-05,
    "WOOD": 4.848e-05,
    "STONE": 8.333e-05,
    "PLANKS": 0.08,
    "SOUP": 0.0499,
    "INGOT": 0.0375,
    "is_cash": false
  },
  {
    "FOOD": "0.000062000000",
    "GOLD": "0.000054550000",
    "WOOD": "0.000047330575",
    "date_update": 1732086684,
    "is_cash": true
  },
  {
    "FOOD": "0.000062000000",
    "GOLD": "0.000054550000",
    "WOOD": "0.000047330575",
    "date_update": 1732087830,
    "is_cash": true
  },
  {
    "date_update": 1732088582,
    "FOOD": 6.2e-05,
    "GOLD": 5.455e-05,
    "WOOD": 4.733e-05,
    "STONE": 8.333e-05,
    "PLANKS": 0.08,
    "SOUP": 0.0499,
    "INGOT": 0.0375,
    "is_cash": true
  },
  {
    "date_update": 1732089330,
    "FOOD": 6.2e-05,
    "GOLD": 5.455e-05,
    "WOOD": 4.733e-05,
    "STONE": 8.333e-05,
    "PLANKS": 0.08,
    "SOUP": 0.0499,
    "INGOT": 0.0375,
    "is_cash": true
  },
  {
    "FOOD": "0.000061857143",
    "GOLD": "0.000054550000",
    "WOOD": "0.000047330000",
    "date_update": 1732091432,
    "is_cash": true
  },
  {
    "date_update": 1732092612,
    "FOOD": 6.186e-05,
    "GOLD": 5.455e-05,
    "WOOD": 4.733e-05,
    "STONE": 8.333e-05,
    "PLANKS": 0.08,
    "SOUP": 0.0499,
    "INGOT": 0.0375,
    "is_cash": true
  },
  {
    "FOOD": "0.000061857143",
    "GOLD": "0.000054550000",
    "WOOD": "0.000047200000",
    "date_update": 1732093979,
    "is_cash": true
  },
  {
    "date_update": 1732095162,
    "FOOD": 6.186e-05,
    "GOLD": 5.455e-05,
    "WOOD": 4.72e-05,
    "STONE": 8.333e-05,
    "PLANKS": 0.08,
    "SOUP": 0.0499,
    "INGOT": 0.0375,
    "is_cash": false
  },
  {
    "date_update": 1732095931,
    "FOOD": 6.186e-05,
    "GOLD": 5.455e-05,
    "WOOD": 4.72e-05,
    "STONE": 8.333e-05,
    "PLANKS": 0.08,
    "SOUP": 0.0499,
    "INGOT": 0.0375,
    "is_cash": false
  },
  {
    "date_update": 1732096673,
    "FOOD": 6.186e-05,
    "GOLD": 5.455e-05,
    "WOOD": 4.72e-05,
    "STONE": 8.333e-05,
    "PLANKS": 0.08,
    "SOUP": 0.0499,
    "INGOT": 0.0375,
    "is_cash": false
  },
  {
    "date_update": 1732098485,
    "FOOD": 6.186e-05,
    "GOLD": 5.455e-05,
    "WOOD": 4.72e-05,
    "STONE": 8.333e-05,
    "PLANKS": 0.08,
    "SOUP": 0.0499,
    "INGOT": 0.0375,
    "is_cash": false
  },
  {
    "date_update": 1732099558,
    "FOOD": 6.157e-05,
    "GOLD": 5.455e-05,
    "WOOD": 4.72e-05,
    "STONE": 8.333e-05,
    "PLANKS": 0.08,
    "SOUP": 0.0499,
    "INGOT": 0.0375,
    "is_cash": false
  },
  {
    "FOOD": "0.000061570000",
    "GOLD": "0.000054550000",
    "WOOD": "0.000047200000",
    "date_update": 1732100320,
    "is_cash": true
  },
  {
    "date_update": 1732101656,
    "FOOD": 6.157e-05,
    "GOLD": 5e-05,
    "WOOD": 4.72e-05,
    "STONE": 8.333e-05,
    "PLANKS": 0.08,
    "SOUP": 0.0499,
    "INGOT": 0.0375,
    "is_cash": false
  },
  {
    "date_update": 1732102513,
    "FOOD": 6.157e-05,
    "GOLD": 5.455e-05,
    "WOOD": 4.72e-05,
    "STONE": 8.333e-05,
    "PLANKS": 0.08,
    "SOUP": 0.0499,
    "INGOT": 0.0375,
    "is_cash": false
  },
  {
    "FOOD": "0.000061570000",
    "GOLD": "0.000054550000",
    "WOOD": "0.000043981481",
    "date_update": 1732103270,
    "is_cash": true
  },
  {
    "date_update": 1732104772,
    "FOOD": 6.157e-05,
    "GOLD": 5.455e-05,
    "WOOD": 4.397e-05,
    "STONE": 8.333e-05,
    "PLANKS": 0.08,
    "SOUP": 0.0499,
    "INGOT": 0.0375,
    "is_cash": false
  },
  {
    "date_update": 1732107335,
    "FOOD": 6.157e-05,
    "GOLD": 5.455e-05,
    "WOOD": 4.397e-05,
    "STONE": 8.333e-05,
    "PLANKS": 0.08,
    "SOUP": 0.0499,
    "INGOT": 0.0375,
    "is_cash": true
  },
  {
    "date_update": 1732109459,
    "FOOD": 6.156e-05,
    "GOLD": 5.455e-05,
    "WOOD": 4.397e-05,
    "STONE": 8.333e-05,
    "PLANKS": 0.08,
    "SOUP": 0.0499,
    "INGOT": 0.0375,
    "is_cash": true
  },
  {
    "date_update": 1732110332,
    "FOOD": 6.156e-05,
    "GOLD": 5.455e-05,
    "WOOD": 4.397e-05,
    "STONE": 8.333e-05,
    "PLANKS": 0.08,
    "SOUP": 0.0499,
    "INGOT": 0.0375,
    "is_cash": true
  },
  {
    "date_update": 1732111080,
    "FOOD": 6.156e-05,
    "GOLD": 5.455e-05,
    "WOOD": 4.397e-05,
    "STONE": 8.333e-05,
    "PLANKS": 0.08,
    "SOUP": 0.0499,
    "INGOT": 0.0375,
    "is_cash": false
  },
  {
    "date_update": 1732112721,
    "FOOD": 6.156e-05,
    "GOLD": 5.2e-05,
    "WOOD": 4.176e-05,
    "STONE": 8.333e-05,
    "PLANKS": 0.08,
    "SOUP": 0.0499,
    "INGOT": 0.0375,
    "is_cash": true
  },
  {
    "FOOD": "0.000061559980",
    "GOLD": "0.000052000000",
    "WOOD": "0.000041759259",
    "date_update": 1732113805,
    "is_cash": true
  },
  {
    "date_update": 1732114562,
    "FOOD": 6.156e-05,
    "GOLD": 5.2e-05,
    "WOOD": 4.176e-05,
    "STONE": 8.333e-05,
    "PLANKS": 0.08,
    "SOUP": 0.0499,
    "INGOT": 0.0375,
    "is_cash": false
  },
  {
    "FOOD": "0.000061559980",
    "GOLD": "0.000052000000",
    "WOOD": "0.000041759259",
    "date_update": 1732116331,
    "is_cash": true
  },
  {
    "FOOD": "0.000061559980",
    "GOLD": "0.000052000000",
    "WOOD": "0.000041759259",
    "date_update": 1732117366,
    "is_cash": true
  },
  {
    "date_update": 1732118130,
    "FOOD": 6.156e-05,
    "GOLD": 5.2e-05,
    "WOOD": 4.176e-05,
    "STONE": 8.333e-05,
    "PLANKS": 0.08,
    "SOUP": 0.0499,
    "INGOT": 0.0375,
    "is_cash": true
  },
  {
    "date_update": 1732120181,
    "FOOD": 6.098e-05,
    "GOLD": 5.2e-05,
    "WOOD": 4.176e-05,
    "STONE": 8.333e-05,
    "PLANKS": 0.08,
    "SOUP": 0.0499,
    "INGOT": 0.0375,
    "is_cash": false
  },
  {
    "date_update": 1732121428,
    "FOOD": 6.098e-05,
    "GOLD": 5.2e-05,
    "WOOD": 4.176e-05,
    "STONE": 8.211e-05,
    "PLANKS": 0.08,
    "SOUP": 0.0499,
    "INGOT": 0.0375,
    "is_cash": false
  },
  {
    "date_update": 1732122686,
    "FOOD": 6.098e-05,
    "GOLD": 5.2e-05,
    "WOOD": 4.176e-05,
    "STONE": 8.211e-05,
    "PLANKS": 0.08,
    "SOUP": 0.0499,
    "INGOT": 0.0375,
    "is_cash": false
  },
  {
    "date_update": 1732123927,
    "FOOD": 6.098e-05,
    "GOLD": 5.2e-05,
    "WOOD": 4.176e-05,
    "STONE": 8.211e-05,
    "PLANKS": 0.08,
    "SOUP": 0.0499,
    "INGOT": 0.0375,
    "is_cash": false
  },
  {
    "FOOD": "0.000060980000",
    "GOLD": "0.000052000000",
    "WOOD": "0.000041760000",
    "date_update": 1732124687,
    "is_cash": true
  },
  {
    "date_update": 1732125454,
    "FOOD": 6.098e-05,
    "GOLD": 5.2e-05,
    "WOOD": 4.021e-05,
    "STONE": 8.211e-05,
    "PLANKS": 0.08,
    "SOUP": 0.0499,
    "INGOT": 0.0375,
    "is_cash": false
  },
  {
    "date_update": 1732127606,
    "FOOD": 6.098e-05,
    "GOLD": 5.2e-05,
    "WOOD": 4e-05,
    "STONE": 8.211e-05,
    "PLANKS": 0.08,
    "SOUP": 0.0499,
    "INGOT": 0.0375,
    "is_cash": false
  },
  {
    "date_update": 1732128614,
    "FOOD": 6.098e-05,
    "GOLD": 5.2e-05,
    "WOOD": 4e-05,
    "STONE": 8.211e-05,
    "PLANKS": 0.08,
    "SOUP": 0.0499,
    "INGOT": 0.0375,
    "is_cash": false
  },
  {
    "date_update": 1732129765,
    "FOOD": 6.098e-05,
    "GOLD": 5.15e-05,
    "WOOD": 4e-05,
    "STONE": 8.211e-05,
    "PLANKS": 0.08,
    "SOUP": 0.0499,
    "INGOT": 0.0375,
    "is_cash": false
  },
  {
    "date_update": 1732130678,
    "FOOD": 6.098e-05,
    "GOLD": 5.15e-05,
    "WOOD": 4e-05,
    "STONE": 8.211e-05,
    "PLANKS": 0.08,
    "SOUP": 0.0499,
    "INGOT": 0.0375,
    "is_cash": false
  },
  {
    "date_update": 1732131512,
    "FOOD": 6.098e-05,
    "GOLD": 5.15e-05,
    "WOOD": 4e-05,
    "STONE": 8.211e-05,
    "PLANKS": 0.08,
    "SOUP": 0.0499,
    "INGOT": 0.0375,
    "is_cash": false
  }
]
