[
  {
    "FOOD": "0.000006000000",
    "GOLD": "0.000006333333",
    "WOOD": "0.000007650000",
    "date_update": 1728265305,
    "is_cash": true
  },
  {
    "date_update": 1728269091,
    "FOOD": "0.000006000000",
    "GOLD": "0.000006333333",
    "WOOD": "0.000007650000",
    "STONE": "0.000020000000",
    "PLANKS": "0.000340000000",
    "SOUP": "0.000500000000",
    "INGOT": "0.000769230000",
    "is_cash": false
  },
  {
    "date_update": 1728270903,
    "FOOD": "0.000006000000",
    "GOLD": "0.000006333333",
    "WOOD": "0.000007650000",
    "STONE": "0.000020000000",
    "PLANKS": "0.000340000000",
    "SOUP": "0.000500000000",
    "INGOT": "0.000769230000",
    "is_cash": false
  },
  {
    "date_update": 1728272361,
    "FOOD": "0.000006000000",
    "GOLD": "0.000006333333",
    "WOOD": "0.000007650000",
    "STONE": "0.000020000000",
    "PLANKS": "0.000340000000",
    "SOUP": "0.000500000000",
    "INGOT": "0.000769230000",
    "is_cash": false
  },
  {
    "FOOD": "0.000006000000",
    "GOLD": "0.000006333333",
    "WOOD": "0.000007650000",
    "date_update": 1728273030,
    "is_cash": true
  },
  {
    "FOOD": "0.000006000000",
    "GOLD": "0.000006333333",
    "WOOD": "0.000007650000",
    "date_update": 1728273616,
    "is_cash": true
  },
  {
    "date_update": 1728275328,
    "FOOD": "0.000006000000",
    "GOLD": "0.000006333330",
    "WOOD": "0.000007650000",
    "STONE": "0.000020000000",
    "PLANKS": "0.000340000000",
    "SOUP": "0.000500000000",
    "INGOT": "0.000769230000",
    "is_cash": false
  },
  {
    "FOOD": "0.000006000000",
    "GOLD": "0.000006333300",
    "WOOD": "0.000007650000",
    "date_update": 1728276231,
    "is_cash": true
  },
  {
    "date_update": 1728276827,
    "FOOD": "0.000006000000",
    "GOLD": "0.000006333300",
    "WOOD": "0.000007650000",
    "STONE": "0.000020000000",
    "PLANKS": "0.000340000000",
    "SOUP": "0.000500000000",
    "INGOT": "0.000769230000",
    "is_cash": true
  },
  {
    "FOOD": "0.000006000000",
    "GOLD": "0.000006333330",
    "WOOD": "0.000007650000",
    "date_update": 1728278049,
    "is_cash": true
  },
  {
    "date_update": 1728279217,
    "FOOD": "0.000006000000",
    "GOLD": "0.000006333330",
    "WOOD": "0.000007650000",
    "STONE": "0.000020000000",
    "PLANKS": "0.000340000000",
    "SOUP": "0.000500000000",
    "INGOT": "0.000769230000",
    "is_cash": false
  },
  {
    "date_update": 1728279836,
    "FOOD": "0.000006000000",
    "GOLD": "0.000006333330",
    "WOOD": "0.000007650000",
    "STONE": "0.000020000000",
    "PLANKS": "0.000340000000",
    "SOUP": "0.000500000000",
    "INGOT": "0.000769230000",
    "is_cash": true
  },
  {
    "FOOD": "0.000006000000",
    "GOLD": "0.000006333300",
    "WOOD": "0.000007650000",
    "date_update": 1728280409,
    "is_cash": true
  },
  {
    "FOOD": "0.000006000000",
    "GOLD": "0.000006333300",
    "WOOD": "0.000007650000",
    "date_update": 1728281884,
    "is_cash": true
  },
  {
    "FOOD": "0.000005500000",
    "GOLD": "0.000006333300",
    "WOOD": "0.000007650000",
    "date_update": 1728283312,
    "is_cash": true
  },
  {
    "date_update": 1728283936,
    "FOOD": "0.000005500000",
    "GOLD": "0.000006333300",
    "WOOD": "0.000007650000",
    "STONE": "0.000020000000",
    "PLANKS": "0.000340000000",
    "SOUP": "0.000500000000",
    "INGOT": "0.000769230000",
    "is_cash": false
  },
  {
    "FOOD": "0.000005500000",
    "GOLD": "0.000006333300",
    "WOOD": "0.000007600000",
    "date_update": 1728285029,
    "is_cash": true
  },
  {
    "FOOD": "0.000005500000",
    "GOLD": "0.000006333300",
    "WOOD": "0.000007600000",
    "date_update": 1728286008,
    "is_cash": true
  },
  {
    "date_update": 1728286646,
    "FOOD": "0.000005500000",
    "GOLD": "0.000006333300",
    "WOOD": "0.000007600000",
    "STONE": "0.000020000000",
    "PLANKS": "0.000340000000",
    "SOUP": "0.000500000000",
    "INGOT": "0.000769230000",
    "is_cash": true
  },
  {
    "FOOD": "0.000005500000",
    "GOLD": "0.000006333300",
    "WOOD": "0.000007600000",
    "date_update": 1728287234,
    "is_cash": true
  },
  {
    "FOOD": "0.000005500000",
    "GOLD": "0.000006333300",
    "WOOD": "0.000007600000",
    "date_update": 1728287811,
    "is_cash": true
  },
  {
    "FOOD": "0.000005500000",
    "GOLD": "0.000006333300",
    "WOOD": "0.000007600000",
    "date_update": 1728289507,
    "is_cash": true
  }
]
