[
  {
    "date_update": 1723426825,
    "FOOD": "0.000010100000",
    "GOLD": "0.000009333333",
    "WOOD": "0.000009666660",
    "STONE": "0.000006666000",
    "PLANKS": "0.000999833333",
    "SOUP": "0.003500000000",
    "INGOT": "0.001398000000",
    "is_cash": true
  },
  {
    "FOOD": "0.000010100000",
    "GOLD": "0.000009333333",
    "WOOD": "0.000009666660",
    "date_update": 1723429812,
    "is_cash": true
  },
  {
    "FOOD": "0.000010100000",
    "GOLD": "0.000009333333",
    "WOOD": "0.000009666660",
    "date_update": 1723431151,
    "is_cash": true
  },
  {
    "FOOD": "0.000010100000",
    "GOLD": "0.000009333333",
    "WOOD": "0.000009636364",
    "date_update": 1723432159,
    "is_cash": true
  },
  {
    "date_update": 1723433345,
    "FOOD": "0.000010100000",
    "GOLD": "0.000009333333",
    "WOOD": "0.000009636364",
    "STONE": "0.000006666000",
    "PLANKS": "0.000999833333",
    "SOUP": "0.003500000000",
    "INGOT": "0.001398000000",
    "is_cash": false
  },
  {
    "date_update": 1723434041,
    "FOOD": "0.000010100000",
    "GOLD": "0.000009333333",
    "WOOD": "0.000009636364",
    "STONE": "0.000006666000",
    "PLANKS": "0.000999833333",
    "SOUP": "0.003500000000",
    "INGOT": "0.001398000000",
    "is_cash": false
  },
  {
    "FOOD": "0.000010100000",
    "GOLD": "0.000009333333",
    "WOOD": "0.000009636364",
    "date_update": 1723434638,
    "is_cash": true
  },
  {
    "FOOD": "0.000010100000",
    "GOLD": "0.000009333333",
    "WOOD": "0.000009636364",
    "date_update": 1723435222,
    "is_cash": true
  },
  {
    "date_update": 1723436738,
    "FOOD": "0.000010100000",
    "GOLD": "0.000009333333",
    "WOOD": "0.000009636364",
    "STONE": "0.000006666000",
    "PLANKS": "0.000999833333",
    "SOUP": "0.003500000000",
    "INGOT": "0.001398000000",
    "is_cash": false
  },
  {
    "FOOD": "0.000010100000",
    "GOLD": "0.000009333333",
    "WOOD": "0.000009636364",
    "date_update": 1723437503,
    "is_cash": true
  },
  {
    "FOOD": "0.000010100000",
    "GOLD": "0.000009330000",
    "WOOD": "0.000009636364",
    "date_update": 1723438097,
    "is_cash": true
  },
  {
    "FOOD": "0.000010100000",
    "GOLD": "0.000009330000",
    "WOOD": "0.000009636364",
    "date_update": 1723438668,
    "is_cash": true
  },
  {
    "FOOD": "0.000010000000",
    "GOLD": "0.000009330000",
    "WOOD": "0.000009636364",
    "date_update": 1723439991,
    "is_cash": true
  },
  {
    "FOOD": "0.000010000000",
    "GOLD": "0.000009333333",
    "WOOD": "0.000009636364",
    "date_update": 1723440825,
    "is_cash": true
  },
  {
    "FOOD": "0.000010000000",
    "GOLD": "0.000009333333",
    "WOOD": "0.000009636364",
    "date_update": 1723441398,
    "is_cash": true
  },
  {
    "FOOD": "0.000010000000",
    "GOLD": "0.000009333333",
    "WOOD": "0.000009636364",
    "date_update": 1723441987,
    "is_cash": true
  },
  {
    "date_update": 1723443341,
    "FOOD": "0.000010000000",
    "GOLD": "0.000009333333",
    "WOOD": "0.000009636364",
    "STONE": "0.000006666000",
    "PLANKS": "0.000999833333",
    "SOUP": "0.003500000000",
    "INGOT": "0.001398000000",
    "is_cash": false
  },
  {
    "FOOD": "0.000010000000",
    "GOLD": "0.000009218750",
    "WOOD": "0.000009636364",
    "date_update": 1723444627,
    "is_cash": true
  },
  {
    "date_update": 1723445219,
    "FOOD": "0.000010000000",
    "GOLD": "0.000009218750",
    "WOOD": "0.000009636364",
    "STONE": "0.000006666000",
    "PLANKS": "0.000980000000",
    "SOUP": "0.003500000000",
    "INGOT": "0.001398000000",
    "is_cash": true
  },
  {
    "date_update": 1723445799,
    "FOOD": "0.000010000000",
    "GOLD": "0.000009218750",
    "WOOD": "0.000009636364",
    "STONE": "0.000006666000",
    "PLANKS": "0.000980000000",
    "SOUP": "0.003500000000",
    "INGOT": "0.001398000000",
    "is_cash": true
  },
  {
    "date_update": 1723446995,
    "FOOD": "0.000010000000",
    "GOLD": "0.000009218750",
    "WOOD": "0.000009636364",
    "STONE": "0.000006666000",
    "PLANKS": "0.000980000000",
    "SOUP": "0.003500000000",
    "INGOT": "0.001398000000",
    "is_cash": true
  },
  {
    "FOOD": "0.000010000000",
    "GOLD": "0.000009000000",
    "WOOD": "0.000009636364",
    "date_update": 1723447595,
    "is_cash": true
  },
  {
    "FOOD": "0.000010000000",
    "GOLD": "0.000009000000",
    "WOOD": "0.000009636364",
    "date_update": 1723448199,
    "is_cash": true
  },
  {
    "date_update": 1723448788,
    "FOOD": "0.000010000000",
    "GOLD": "0.000009218750",
    "WOOD": "0.000009636364",
    "STONE": "0.000006666000",
    "PLANKS": "0.000980000000",
    "SOUP": "0.003500000000",
    "INGOT": "0.001333333333",
    "is_cash": false
  },
  {
    "date_update": 1723449363,
    "FOOD": "0.000010000000",
    "GOLD": "0.000009218750",
    "WOOD": "0.000009636364",
    "STONE": "0.000006666000",
    "PLANKS": "0.000980000000",
    "SOUP": "0.003500000000",
    "INGOT": "0.001333333333",
    "is_cash": true
  },
  {
    "date_update": 1723450893,
    "FOOD": "0.000010000000",
    "GOLD": "0.000009218750",
    "WOOD": "0.000009636364",
    "STONE": "0.000006666000",
    "PLANKS": "0.000980000000",
    "SOUP": "0.003500000000",
    "INGOT": "0.001333333333",
    "is_cash": false
  },
  {
    "FOOD": "0.000010000000",
    "GOLD": "0.000009210000",
    "WOOD": "0.000009630000",
    "date_update": 1723451848,
    "is_cash": true
  },
  {
    "FOOD": "0.000010000000",
    "GOLD": "0.000009210000",
    "WOOD": "0.000009630000",
    "date_update": 1723452420,
    "is_cash": true
  },
  {
    "date_update": 1723453011,
    "FOOD": "0.000010000000",
    "GOLD": "0.000009218750",
    "WOOD": "0.000009630000",
    "STONE": "0.000006666000",
    "PLANKS": "0.000980000000",
    "SOUP": "0.003500000000",
    "INGOT": "0.001333333333",
    "is_cash": false
  },
  {
    "FOOD": "0.000010000000",
    "GOLD": "0.000009218750",
    "WOOD": "0.000009630000",
    "date_update": 1723454352,
    "is_cash": true
  },
  {
    "date_update": 1723455041,
    "FOOD": "0.000010000000",
    "GOLD": "0.000009218750",
    "WOOD": "0.000009630000",
    "STONE": "0.000006666000",
    "PLANKS": "0.000980000000",
    "SOUP": "0.003500000000",
    "INGOT": "0.001333333333",
    "is_cash": true
  },
  {
    "FOOD": "0.000010000000",
    "GOLD": "0.000009218750",
    "WOOD": "0.000009630000",
    "date_update": 1723455620,
    "is_cash": true
  },
  {
    "FOOD": "0.000010000000",
    "GOLD": "0.000009218750",
    "WOOD": "0.000009630000",
    "date_update": 1723456208,
    "is_cash": true
  },
  {
    "FOOD": "0.000010000000",
    "GOLD": "0.000009218750",
    "WOOD": "0.000009630000",
    "date_update": 1723456783,
    "is_cash": true
  },
  {
    "FOOD": "0.000010000000",
    "GOLD": "0.000009218750",
    "WOOD": "0.000009630000",
    "date_update": 1723458249,
    "is_cash": true
  },
  {
    "FOOD": "0.000010000000",
    "GOLD": "0.000009218750",
    "WOOD": "0.000009630000",
    "date_update": 1723459066,
    "is_cash": true
  },
  {
    "FOOD": "0.000010000000",
    "GOLD": "0.000009218750",
    "WOOD": "0.000009630000",
    "date_update": 1723459657,
    "is_cash": true
  },
  {
    "date_update": 1723460256,
    "FOOD": "0.000010000000",
    "GOLD": "0.000009218750",
    "WOOD": "0.000009630000",
    "STONE": "0.000006500000",
    "PLANKS": "0.000980000000",
    "SOUP": "0.003500000000",
    "INGOT": "0.001333333333",
    "is_cash": false
  },
  {
    "date_update": 1723461421,
    "FOOD": "0.000010000000",
    "GOLD": "0.000009218750",
    "WOOD": "0.000009400000",
    "STONE": "0.000006500000",
    "PLANKS": "0.000980000000",
    "SOUP": "0.003500000000",
    "INGOT": "0.001333333333",
    "is_cash": true
  },
  {
    "FOOD": "0.000010000000",
    "GOLD": "0.000009218750",
    "WOOD": "0.000009400000",
    "date_update": 1723462002,
    "is_cash": true
  },
  {
    "FOOD": "0.000010000000",
    "GOLD": "0.000009218750",
    "WOOD": "0.000009400000",
    "date_update": 1723462623,
    "is_cash": true
  },
  {
    "FOOD": "0.000010000000",
    "GOLD": "0.000009218750",
    "WOOD": "0.000009400000",
    "date_update": 1723463201,
    "is_cash": true
  },
  {
    "FOOD": "0.000010000000",
    "GOLD": "0.000009333333",
    "WOOD": "0.000009630000",
    "date_update": 1723463783,
    "is_cash": true
  },
  {
    "FOOD": "0.000010000000",
    "GOLD": "0.000009333333",
    "WOOD": "0.000009630000",
    "date_update": 1723466060,
    "is_cash": true
  },
  {
    "date_update": 1723467603,
    "FOOD": "0.000010000000",
    "GOLD": "0.000009333333",
    "WOOD": "0.000009630000",
    "STONE": "0.000006500000",
    "PLANKS": "0.000980000000",
    "SOUP": "0.003500000000",
    "INGOT": "0.001333333333",
    "is_cash": false
  },
  {
    "FOOD": "0.000010000000",
    "GOLD": "0.000009333333",
    "WOOD": "0.000009630000",
    "date_update": 1723469138,
    "is_cash": true
  },
  {
    "FOOD": "0.000010000000",
    "GOLD": "0.000009333333",
    "WOOD": "0.000009630000",
    "date_update": 1723469800,
    "is_cash": true
  },
  {
    "date_update": 1723470430,
    "FOOD": "0.000010000000",
    "GOLD": "0.000009333333",
    "WOOD": "0.000009630000",
    "STONE": "0.000006500000",
    "PLANKS": "0.000980000000",
    "SOUP": "0.003500000000",
    "INGOT": "0.001333333333",
    "is_cash": false
  },
  {
    "FOOD": "0.000010000000",
    "GOLD": "0.000009333333",
    "WOOD": "0.000009630000",
    "date_update": 1723470964,
    "is_cash": true
  },
  {
    "FOOD": "0.000010000000",
    "GOLD": "0.000009333333",
    "WOOD": "0.000009630000",
    "date_update": 1723472199,
    "is_cash": true
  },
  {
    "FOOD": "0.000010000000",
    "GOLD": "0.000009333333",
    "WOOD": "0.000009600000",
    "date_update": 1723473194,
    "is_cash": true
  },
  {
    "FOOD": "0.000010000000",
    "GOLD": "0.000009000000",
    "WOOD": "0.000009333333",
    "date_update": 1723473785,
    "is_cash": true
  },
  {
    "date_update": 1723474380,
    "FOOD": "0.000010000000",
    "GOLD": "0.000009000000",
    "WOOD": "0.000009333333",
    "STONE": "0.000006500000",
    "PLANKS": "0.000980000000",
    "SOUP": "0.003500000000",
    "INGOT": "0.001333333333",
    "is_cash": false
  },
  {
    "FOOD": "0.000010000000",
    "GOLD": "0.000009000000",
    "WOOD": "0.000009333333",
    "date_update": 1723475506,
    "is_cash": true
  },
  {
    "FOOD": "0.000010000000",
    "GOLD": "0.000009000000",
    "WOOD": "0.000009333333",
    "date_update": 1723476526,
    "is_cash": true
  },
  {
    "FOOD": "0.000010000000",
    "GOLD": "0.000009000000",
    "WOOD": "0.000009333333",
    "date_update": 1723477195,
    "is_cash": true
  }
]
