[
  {
    "FOOD": "0.000009333333",
    "GOLD": "0.000028490000",
    "WOOD": "0.000019295493",
    "date_update": 1724204285,
    "is_cash": true
  },
  {
    "FOOD": "0.000009333333",
    "GOLD": "0.000028480000",
    "WOOD": "0.000019295493",
    "date_update": 1724207211,
    "is_cash": true
  },
  {
    "FOOD": "0.000009333333",
    "GOLD": "0.000028480000",
    "WOOD": "0.000019295493",
    "date_update": 1724208531,
    "is_cash": true
  },
  {
    "FOOD": "0.000009333333",
    "GOLD": "0.000028480000",
    "WOOD": "0.000019295493",
    "date_update": 1724209118,
    "is_cash": true
  },
  {
    "FOOD": "0.000009333333",
    "GOLD": "0.000028480000",
    "WOOD": "0.000019295493",
    "date_update": 1724210573,
    "is_cash": true
  },
  {
    "FOOD": "0.000009333333",
    "GOLD": "0.000028480000",
    "WOOD": "0.000019295493",
    "date_update": 1724211311,
    "is_cash": true
  }
]
